<planet>
	<id>KOI 1192.01</id>
	<stellarid>KOI 1192</stellarid>
	<properties>
		<radius>3.2032195</radius>
		<mass>4.81197631259</mass>
		<orbit>
			<period>201292</period>
			<semimajoraxis>99</semimajoraxis>
			<eccentricity>-1</eccentricity>
			<inclination>-1</inclination>
		</orbit>
	</properties>
	<star>
		<kic>3644071</kic>
		<temperature>5399</temperature>
		<mass>-1</mass>
		<radius>1.00</radius>
		<metallicity>0</metallicity>
		<rightascension>19 24 07</rightascension>
		<declination>+38 42 14</declination>
		<distance>654.103459002</distance>
		<mag>14.215</mag>
	</star>
	<multiplicity>1</multiplicity>
</planet>
