<planet>
	<id>KOI 2095.01</id>
	<stellarid>KOI 2095</stellarid>
	<properties>
		<radius>0.0847509</radius>
		<mass>0.0027088950298</mass>
		<orbit>
			<period>1.4347788</period>
			<semimajoraxis>0.023</semimajoraxis>
			<eccentricity>-1</eccentricity>
			<inclination>-1</inclination>
		</orbit>
	</properties>
	<star>
		<kic>7918992</kic>
		<temperature>5484</temperature>
		<mass>-1</mass>
		<radius>0.71</radius>
		<metallicity>0</metallicity>
		<rightascension>19 59 08</rightascension>
		<declination>+43 40 14</declination>
		<distance>596.585964489</distance>
		<mag>14.691</mag>
	</star>
	<multiplicity>1</multiplicity>
</planet>
