<planet>
	<id>KOI 2579.01</id>
	<stellarid>KOI 2579</stellarid>
	<properties>
		<radius>0.1266707</radius>
		<mass>0.00619908784849</mass>
		<orbit>
			<period>2.7296513</period>
			<semimajoraxis>0.038</semimajoraxis>
			<eccentricity>-1</eccentricity>
			<inclination>-1</inclination>
		</orbit>
	</properties>
	<star>
		<kic>9896018</kic>
		<temperature>5938</temperature>
		<mass>-1</mass>
		<radius>1.09</radius>
		<metallicity>0</metallicity>
		<rightascension>19 35 57</rightascension>
		<declination>+46 43 04</declination>
		<distance>1324.72787627</distance>
		<mag>15.147</mag>
	</star>
	<multiplicity>1</multiplicity>
</planet>
