<planet>
	<bibliography>
		<paper>
			<bibcode>2012Natur.481..448S</bibcode>
			<title>Astronomy: A new class of planet</title>
			<authors>Southworth, John</authors>
			<journal>Nature, Volume 481, Issue 7382, pp. 448-449 (2012).</journal>
			<date>1/2012</date>
			<url>http://adsabs.harvard.edu/abs/2012Natur.481..448S</url>
		</paper>
		<paper>
			<bibcode>2012ApJ...745....2L</bibcode>
			<title>Interaction of Close-in Planets with the Magnetosphere of Their Host Stars. II. Super-Earths as Unipolar Inductors and Their Orbital Evolution</title>
			<authors>Laine, Randy O.; Lin, Douglas N. C.</authors>
			<journal>The Astrophysical Journal, Volume 745, Issue 1, article id. 2 (2012).</journal>
			<date>1/2012</date>
			<url>http://adsabs.harvard.edu/abs/2012ApJ...745....2L</url>
		</paper>
		<paper>
			<bibcode>2012AN....333...26P</bibcode>
			<title>A magnetic cycle of tau Bootis? The coronal and chromospheric view</title>
			<authors>