<planet>
	<bibliography>
		<paper>
			<bibcode>2011ApJ...735...72G</bibcode>
			<title>Effects of Stellar Flux on Tidally Locked Terrestrial Planets: Degree-1 Mantle Convection and Local Magma Ponds</title>
			<authors>Gelman, S. E.; Elkins-Tanton, L. T.; Seager, S.</authors>
			<journal>The Astrophysical Journal, Volume 735, Issue 2, article id. 72 (2011).</journal>
			<date>7/2011</date>
			<url>http://adsabs.harvard.edu/abs/2011ApJ...735...72G</url>
		</paper>
		<paper>
			<bibcode>2011ApJ...733...68B</bibcode>
			<title>Density Estimation for Projected Exoplanet Quantities</title>
			<authors>Brown, Robert A.</authors>
			<journal>The Astrophysical Journal, Volume 733, Issue 1, article id. 68 (2011).</journal>
			<date>5/2011</date>
			<url>http://adsabs.harvard.edu/abs/2011ApJ...733...68B</url>
		</paper>
		<paper>
			<bibcode>2011ApJ...727..103T</bibcode>
			<title>The Anglo-Australian Planet Search. XX. A Solitary Ice-giant Planet Orbiting HD 102365</title>
			<authors>Tinney, C. G.; Butler, R. Paul; Jones, Hugh R. A.; Wittenmyer, Robert A.; O'Toole, Simon; Bailey, Jeremy; Carter, Brad D.</authors>
			<journal>The Astrophysical Journal, Volume 727, Issue 2, article id. 103 (2011).</journal>
			<date>2/2011</date>
			<url>http://adsabs.harvard.edu/abs/2011ApJ...727..103T</url>
		</paper>
		<paper>
			<bibcode>2010MNRAS.406.1918D</bibcode>
			<title>The Hill stability of the possible moons of extrasolar planets</title>
			<authors>Donnison, J. R.</authors>
			<journal>Monthly Notices of the Royal Astronomical Society, Volume 406, Issue 3, pp. 1918-1934.</journal>
			<date>8/2010</date>
			<url>http://adsabs.harvard.edu/abs/2010MNRAS.406.1918D</url>
		</paper>
		<paper>
			<bibcode>2010ApJ...718..543M</bibcode>
			<title>Systemic: A Testbed for Characterizing the Detection of Extrasolar Planets. II. Numerical Approaches to the Transit Timing Inverse Problem</title>
			<authors>Meschiari, Stefano; Laughlin, Gregory P.</authors>
			<journal>The Astrophysical Journal, Volume 718, Issue 1, pp. 543-550 (2010).</journal>
			<date>7/2010</date>
			<url>http://adsabs.harvard.edu/abs/2010ApJ...718..543M</url>
		</paper>
		<paper>
			<bibcode>2010A&amp;A...518A..25G</bibcode>
			<title>The Spitzer search for the transits of HARPS low-mass planets. I. No transit for the super-Earth HD 40307b</title>
			<authors>Gillon, M.; Deming, D.; Demory, B.-O.; Lovis, C.; Seager, S.; Mayor, M.; Pepe, F.; Queloz, D.; Segransan, D.; Udry, S.; Delmelle, S.; Magain, P.</authors>
			<journal>Astronomy and Astrophysics, Volume 518, id.A25</journal>
			<date>7/2010</date>
			<url>http://adsabs.harvard.edu/abs/2010A%26A...518A..25G</url>
		</paper>
		<paper>
			<bibcode>2010A&amp;A...516A..82F</bibcode>
			<title>The stability of ultra-compact planetary systems</title>
			<authors>Funk, B.; Wuchterl, G.; Schwarz, R.; Pilat-Lohinger, E.; Eggl, S.</authors>
			<journal>Astronomy and Astrophysics, Volume 516, id.A82</journal>
			<date>6/2010</date>
			<url>http://adsabs.harvard.edu/abs/2010A%26A...516A..82F</url>
		</paper>
		<paper>
			<bibcode>2009ApJ...700.1732K</bibcode>
			<title>Geodynamics and Rate of Volcanism on Massive Earth-like Planets</title>
			<authors>Kite, E. S.; Manga, M.; Gaidos, E.</authors>
			<journal>The Astrophysical Journal, Volume 700, Issue 2, pp. 1732-1749 (2009).</journal>
			<date>8/2009</date>
			<url>http://adsabs.harvard.edu/abs/2009ApJ...700.1732K</url>
		</paper>
		<paper>
			<bibcode>2009ApJ...698..519K</bibcode>
			<title>Transits of Earth-like Planets</title>
			<authors>Kaltenegger, Lisa; Traub, Wesley A.</authors>
			<journal>The Astrophysical Journal, Volume 698, Issue 1, pp. 519-527 (2009).</journal>
			<date>6/2009</date>
			<url>http://adsabs.harvard.edu/abs/2009ApJ...698..519K</url>
		</paper>
		<paper>
			<bibcode>2009ApJ...696...75H</bibcode>
			<title>The NASA-UC Eta-Earth Program. I. A Super-Earth Orbiting HD 7924</title>
			<authors>Howard, Andrew W.; Johnson, John Asher; Marcy, Geoffrey W.; Fischer, Debra A.; Wright, Jason T.; Henry, Gregory W.; Giguere, Matthew J.; Isaacson, Howard; Valenti, Jeff A.; Anderson, Jay; Piskunov, Nikolai E.</authors>
			<journal>The Astrophysical Journal, Volume 696, Issue 1, pp. 75-83 (2009).</journal>
			<date>5/2009</date>
			<url>http://adsabs.harvard.edu/abs/2009ApJ...696...75H</url>
		</paper>
		<paper>
			<bibcode>2009ApJ...695.1006B</bibcode>
			<title>The HD 40307 Planetary System: Super-Earths or Mini-Neptunes?</title>
			<authors>Barnes, Rory; Jackson, Brian; Raymond, Sean N.; West, Andrew A.; Greenberg, Richard</authors>
			<journal>The Astrophysical Journal, Volume 695, Issue 2, pp. 1006-1011 (2009).</journal>
			<date>4/2009</date>
			<url>http://adsabs.harvard.edu/abs/2009ApJ...695.1006B</url>
		</paper>
		<paper>
			<bibcode>2009ApJ...694..107B</bibcode>
			<title>Analytical Solutions for Radiative Transfer: Implications for Giant Planet Formation by Disk Instability</title>
			<authors>Boss, Alan P.</authors>
			<journal>The Astrophysical Journal, Volume 694, Issue 1, pp. 107-114 (2009).</journal>
			<date>3/2009</date>
			<url>http://adsabs.harvard.edu/abs/2009ApJ...694..107B</url>
		</paper>
		<paper>
			<bibcode>2009ApJ...693.1084W</bibcode>
			<title>Ten New and Updated Multiplanet Systems and a Survey of Exoplanetary Systems</title>
			<authors>Wright, J. T.; Upadhyay, S.; Marcy, G. W.; Fischer, D. A.; Ford, Eric B.; Johnson, John Asher</authors>
			<journal>The Astrophysical Journal, Volume 693, Issue 2, pp. 1084-1099 (2009).</journal>
			<date>3/2009</date>
			<url>http://adsabs.harvard.edu/abs/2009ApJ...693.1084W</url>
		</paper>
		<paper>
			<bibcode>2009ApJ...693..722G</bibcode>
			<title>A Study of the Accuracy of Mass-Radius Relationships for Silicate-Rich and Ice-Rich Planets up to 100 Earth Masses</title>
			<authors>Grasset, O.; Schneider, J.; Sotin, C.</authors>
			<journal>The Astrophysical Journal, Volume 693, Issue 1, pp. 722-733 (2009).</journal>
			<date>3/2009</date>
			<url>http://adsabs.harvard.edu/abs/2009ApJ...693..722G</url>
		</paper>
		<paper>
			<bibcode>2009A&amp;A...493..639M</bibcode>
			<title>The HARPS search for southern extra-solar planets. XIII. A planetary system with 3 super-Earths (4.2, 6.9, and 9.2 M&amp;oplus;)</title>
			<authors>Mayor, M.; Udry, S.; Lovis, C.; Pepe, F.; Queloz, D.; Benz, W.; Bertaux, J.-L.; Bouchy, F.; Mordasini, C.; Segransan, D.</authors>
			<journal>Astronomy and Astrophysics, Volume 493, Issue 2, 2009, pp.639-644</journal>
			<date>1/2009</date>
			<url>http://adsabs.harvard.edu/abs/2009A%26A...493..639M</url>
		</paper>
		<paper>
			<bibcode>2009PABei..27..301J</bibcode>
			<title>Internal structure and atmospheric composition of Super-Earths.</title>
			<authors>Jin, S.; Ji, J.-H.</authors>
			<journal>Progress in Astronomy, 27, 301-314 (2009)</journal>
			<date>0/2009</date>
			<url>http://adsabs.harvard.edu/abs/2009PABei..27..301J</url>
		</paper>
		<paper>
			<bibcode>2008MNRAS.391..237J</bibcode>
			<title>Tidal heating of terrestrial extrasolar planets and implications for their habitability</title>
			<authors>Jackson, Brian; Barnes, Rory; Greenberg, Richard</authors>
			<journal>Monthly Notices of the Royal Astronomical Society, Volume 391, Issue 1, pp. 237-245.</journal>
			<date>11/2008</date>
			<url>http://adsabs.harvard.edu/abs/2008MNRAS.391..237J</url>
		</paper>
	</bibliography>
	<bibliographystar>
		<paper>
			<bibcode>2011ApJ...741L..23K</bibcode>
			<title>On the Ages of Planetary Systems with Mean-motion Resonances</title>
			<authors>Koriski, Shuki; Zucker, Shay</authors>
			<journal>The Astrophysical Journal Letters, Volume 741, Issue 1, article id. L23 (2011).</journal>
			<date>11/2011</date>
			<url>http://adsabs.harvard.edu/abs/2011ApJ...741L..23K</url>
		</paper>
		<paper>
			<bibcode>2011A&amp;A...535A..17B</bibcode>
			<title>Bisectors of the HARPS cross-correlation function. The dependence on stellar atmospheric parameters</title>
			<authors>