<planet>
	<bibliography>
		<paper>
			<bibcode>2011ApJ...733...68B</bibcode>
			<title>Density Estimation for Projected Exoplanet Quantities</title>
			<authors>Brown, Robert A.</authors>
			<journal>The Astrophysical Journal, Volume 733, Issue 1, article id. 68 (2011).</journal>
			<date>5/2011</date>
			<url>http://cdsads.u-strasbg.fr/abs/2011ApJ...733...68B</url>
		</paper>
		<paper>
			<bibcode>2011ApJ...727..103T</bibcode>
			<title>The Anglo-Australian Planet Search. XX. A Solitary Ice-giant Planet Orbiting HD 102365</title>
			<authors>Tinney, C. G.; Butler, R. Paul; Jones, Hugh R. A.; Wittenmyer, Robert A.; O'Toole, Simon; Bailey, Jeremy; Carter, Brad D.</authors>
			<journal>The Astrophysical Journal, Volume 727, Issue 2, article id. 103 (2011).</journal>
			<date>2/2011</date>
			<url>http://cdsads.u-strasbg.fr/abs/2011ApJ...727..103T</url>
		</paper>
		<paper>
			<bibcode>2011ApJ...727..102W</bibcode>
			<title>On the Frequency of Jupiter Analogs</title>
			<authors>Wittenmyer, Robert A.; Tinney, C. G.; O'Toole, Simon J.; Jones, H. R. A.; Butler, R. P.; Carter, B. D.; Bailey, J.</authors>
			<journal>The Astrophysical Journal, Volume 727, Issue 2, article id. 102 (2011).</journal>
			<date>2/2011</date>
			<url>http://cdsads.u-strasbg.fr/abs/2011ApJ...727..102W</url>
		</paper>
		<paper>
			<bibcode>2010MNRAS.406.1918D</bibcode>
			<title>The Hill stability of the possible moons of extrasolar planets</title>
			<authors>Donnison, J. R.</authors>
			<journal>Monthly Notices of the Royal Astronomical Society, Volume 406, Issue 3, pp. 1918-1934.</journal>
			<date>8/2010</date>
			<url>http://cdsads.u-strasbg.fr/abs/2010MNRAS.406.1918D</url>
		</paper>
		<paper>
			<bibcode>2010ApJ...714..532Z</bibcode>
			<title>On the Orbital Evolution of a Giant Planet Pair Embedded in a Gaseous Disk. I. Jupiter-Saturn Configuration</title>
			<authors>Zhang, Hui; Zhou, Ji-Lin</authors>
			<journal>The Astrophysical Journal, Volume 714, Issue 1, pp. 532-548 (2010).</journal>
			<date>5/2010</date>
			<url>http://cdsads.u-strasbg.fr/abs/2010ApJ...714..532Z</url>
		</paper>
		<paper>
			<bibcode>2010A&amp;A...513A..49S</bibcode>
			<title>New seismic analysis of the exoplanet-host star mu Arae</title>
			<authors>Soriano, M.; Vauclair, S.</authors>
			<journal>Astronomy and Astrophysics, Volume 513, id.A49</journal>
			<date>4/2010</date>
			<url>http://cdsads.u-strasbg.fr/abs/2010A%26A...513A..49S</url>
		</paper>
		<paper>
			<bibcode>2010A&amp;A...511L...8S</bibcode>
			<title>A scenario of planet erosion by coronal radiation</title>
			<authors>Sanz-Forcada, J.; Ribas, I.; Micela, G.; Pollock, A. M. T.; Garc&#237;a-&#193; lvarez, D.; Solano, E.; Eiroa, C.</authors>
			<journal>Astronomy and Astrophysics, Volume 511, id.L8</journal>
			<date>2/2010</date>
			<url>http://cdsads.u-strasbg.fr/abs/2010A%26A...511L...8S</url>
		</paper>
		<paper>
			<bibcode>2010ApJS..186...48J</bibcode>
			<title>On the Fundamental Mass-Period Functions of Extrasolar Planets</title>
			<authors>Jiang, Ing-Guey; Yeh, Li-Chin; Chang, Yen-Chang; Hung, Wen-Liang</authors>
			<journal>The Astrophysical Journal Supplement, Volume 186, Issue 1, pp. 48-62 (2010).</journal>
			<date>1/2010</date>
			<url>http://cdsads.u-strasbg.fr/abs/2010ApJS..186...48J</url>
		</paper>
		<paper>
			<bibcode>2010ApJ...709..168A</bibcode>
			<title>How Eccentric Orbital Solutions Can Hide Planetary Systems in 2:1 Resonant Orbits</title>
			<authors>Anglada-Escud&#233;, Guillem; L&#243;pez-Morales, Mercedes; Chambers, John E.</authors>
			<journal>The Astrophysical Journal, Volume 709, Issue 1, pp. 168-178 (2010).</journal>
			<date>1/2010</date>
			<url>http://cdsads.u-strasbg.fr/abs/2010ApJ...709..168A</url>
		</paper>
		<paper>
			<bibcode>2009ApJ...698.1357J</bibcode>
			<title>Observational Evidence for Tidal Destruction of Exoplanets</title>
			<authors>Jackson, Brian; Barnes, Rory; Greenberg, Richard</authors>
			<journal>The Astrophysical Journal, Volume 698, Issue 2, pp. 1357-1366 (2009).</journal>
			<date>6/2009</date>
			<url>http://cdsads.u-strasbg.fr/abs/2009ApJ...698.1357J</url>
		</paper>
		<paper>
			<bibcode>2009ApJ...697.1263O</bibcode>
			<title>A Neptune-mass Planet Orbiting the Nearby G Dwarf HD 16417</title>
			<authors>O'Toole, Simon; Tinney, C. G.; Butler, R. Paul; Jones, Hugh R. A.; Bailey, Jeremy; Carter, Brad D.; Vogt, Steven S.; Laughlin, Gregory; Rivera, Eugenio J.</authors>
			<journal>The Astrophysical Journal, Volume 697, Issue 2, pp. 1263-1268 (2009).</journal>
			<date>6/2009</date>
			<url>http://cdsads.u-strasbg.fr/abs/2009ApJ...697.1263O</url>
		</paper>
		<paper>
			<bibcode>2009PASP..121..309J</bibcode>
			<title>International Year of Astronomy Invited Review on Exoplanets</title>
			<authors>Johnson, John Asher</authors>
			<journal>Publications of the Astronomical Society of the Pacific, Volume 121, issue 878, pp.309-315</journal>
			<date>4/2009</date>
			<url>http://cdsads.u-strasbg.fr/abs/2009PASP..121..309J</url>
		</paper>
		<paper>
			<bibcode>2009MNRAS.393..969B</bibcode>
			<title>Accounting for velocity jitter in planet search surveys</title>
			<authors>Baluev, Roman V.</authors>
			<journal>Monthly Notices of the Royal Astronomical Society, Volume 393, Issue 3, pp. 969-978.</journal>
			<date>3/2009</date>
			<url>http://cdsads.u-strasbg.fr/abs/2009MNRAS.393..969B</url>
		</paper>
		<paper>
			<bibcode>2009ApJ...693.1084W</bibcode>
			<title>Ten New and Updated Multiplanet Systems and a Survey of Exoplanetary Systems</title>
			<authors>Wright, J. T.; Upadhyay, S.; Marcy, G. W.; Fischer, D. A.; Ford, Eric B.; Johnson, John Asher</authors>
			<journal>The Astrophysical Journal, Volume 693, Issue 2, pp. 1084-1099 (2009).</journal>
			<date>3/2009</date>
			<url>http://cdsads.u-strasbg.fr/abs/2009ApJ...693.1084W</url>
		</paper>
		<paper>
			<bibcode>2008NewA...13..541T</bibcode>
			<title>Seismic analysis of 70 Ophiuchi A: A new quantity proposed</title>
			<authors>Tang, Y. K.; Bi, S. L.; Gai, N.</authors>
			<journal>New Astronomy, Volume 13, Issue 8, p. 541-548.</journal>
			<date>11/2008</date>
			<url>http://cdsads.u-strasbg.fr/abs/2008NewA...13..541T</url>
		</paper>
		<paper>
			<bibcode>2008ApJ...687L.107R</bibcode>
			<title>Mean Motion Resonances from Planet-Planet Scattering</title>
			<authors>Raymond, Sean N.; Barnes, Rory; Armitage, Philip J.; Gorelick, Noel</authors>
			<journal>The Astrophysical Journal, Volume 687, Issue 2, pp. L107-L110.</journal>
			<date>11/2008</date>
			<url>http://cdsads.u-strasbg.fr/abs/2008ApJ...687L.107R</url>
		</paper>
		<paper>
			<bibcode>2008A&amp;A...490..843J</bibcode>
			<title>Radio emission from exoplanets: the role of the stellar coronal density and magnetic field strength</title>
			<authors>Jardine, M.; Collier Cameron, A.</authors>
			<journal>Astronomy and Astrophysics, Volume 490, Issue 2, 2008, pp.843-851</journal>
			<date>11/2008</date>
			<url>http://cdsads.u-strasbg.fr/abs/2008A%26A...490..843J</url>
		</paper>
		<paper>
			<bibcode>2008MNRAS.386L..43S</bibcode>
			<title>New solutions for the planetary dynamics in HD160691 using a Newtonian model and latest data</title>
			<authors>Short, D.; Windmiller, G.; Orosz, J. A.</authors>
			<journal>Monthly Notices of the Royal Astronomical Society: Letters, Volume 386, Issue 1, pp. L43-L46.</journal>
			<date>5/2008</date>
			<url>http://cdsads.u-strasbg.fr/abs/2008MNRAS.386L..43S</url>
		</paper>
		<paper>
			<bibcode>2008A&amp;A...482..699C</bibcode>
			<title>Double-blind test program for astrometric planet detection with Gaia</title>
			<authors>Casertano, S.; Lattanzi, M. G.; Sozzetti, A.; Spagna, A.; Jancart, S.; Morbidelli, R.; Pannunzio, R.; Pourbaix, D.; Queloz, D.</authors>
			<journal>Astronomy and Astrophysics, Volume 482, Issue 2, 2008, pp.699-729</journal>
			<date>5/2008</date>
			<url>http://cdsads.u-strasbg.fr/abs/2008A%26A...482..699C</url>
		</paper>
		<paper>
			<bibcode>2008ApJ...672.1202B</bibcode>
			<title>Detection of a Third Planet in the HD 74156 System Using the Hobby-Eberly Telescope</title>
			<authors>Bean, Jacob L.; McArthur, Barbara E.; Benedict, G. Fritz; Armstrong, Amber</authors>
			<journal>The Astrophysical Journal, Volume 672, Issue 2, pp. 1202-1208.</journal>
			<date>1/2008</date>
			<url>http://cdsads.u-strasbg.fr/abs/2008ApJ...672.1202B</url>
		</paper>
		<paper>
			<bibcode>2007A&amp;A...475..359G</bibcode>
			<title>Predicting low-frequency radio fluxes of known extrasolar planets</title>
			<authors>Grie&#223;meier, J.-M.; Zarka, P.; Spreeuw, H.</authors>
			<journal>Astronomy and Astrophysics, Volume 475, Issue 1, November III 2007, pp.359-368</journal>
			<date>11/2007</date>
			<url>http://cdsads.u-strasbg.fr/abs/2007A%26A...475..359G</url>
		</paper>
		<paper>
			<bibcode>2007ApJ...666..475M</bibcode>
			<title>Extrasolar Planet Taxonomy: A New Statistical Approach</title>
			<authors>Marchi, S.</authors>
			<journal>The Astrophysical Journal, Volume 666, Issue 1, pp. 475-485.</journal>
			<date>9/2007</date>
			<url>http://cdsads.u-strasbg.fr/abs/2007ApJ...666..475M</url>
		</paper>
		<paper>
			<bibcode>2007ApJ...661.1311V</bibcode>
			<title>Extrasolar Planetary Dynamics with a Generalized Planar Laplace-Lagrange Secular Theory</title>
			<authors>Veras, Dimitri; Armitage, Philip J.</authors>
			<journal>The Astrophysical Journal, Volume 661, Issue 2, pp. 1311-1322.</journal>
			<date>6/2007</date>
			<url>http://cdsads.u-strasbg.fr/abs/2007ApJ...661.1311V</url>
		</paper>
		<paper>
			<bibcode>2007MNRAS.376.1727I</bibcode>
			<title>A model-independent test of the spatial variations of the Newtonian gravitational constant in some extrasolar planetary systems</title>
			<authors>Iorio, Lorenzo</authors>
			<journal>Monthly Notices of the Royal Astronomical Society, Volume 376, Issue 4, pp. 1727-1730.</journal>
			<date>4/2007</date>
			<url>http://cdsads.u-strasbg.fr/abs/2007MNRAS.376.1727I</url>
		</paper>
		<paper>
			<bibcode>2007ApJ...657..546G</bibcode>
			<title>On the Extrasolar Multiplanet System around HD 160691</title>
			<authors>Gozdziewski, Krzysztof; Maciejewski, Andrzej J.; Migaszewski, Cezary</authors>
			<journal>The Astrophysical Journal, Volume 657, Issue 1, pp. 546-558.</journal>
			<date>3/2007</date>
			<url>http://cdsads.u-strasbg.fr/abs/2007ApJ...657..546G</url>
		</paper>
		<paper>
			<bibcode>2007A&amp;A...462.1165S</bibcode>
			<title>Trojan planets in HD 108874?</title>
			<authors>Schwarz, R.; Dvorak, R.; Pilat Lohinger, E.; S&#252;li, &#193;.; &#201;rdi, B.</authors>
			<journal>Astronomy and Astrophysics, Volume 462, Issue 3, February II 2007, pp.1165-1170</journal>
			<date>2/2007</date>
			<url>http://cdsads.u-strasbg.fr/abs/2007A%26A...462.1165S</url>
		</paper>
		<paper>
			<bibcode>2007A&amp;A...462..769P</bibcode>
			<title>The HARPS search for southern extra-solar planets. VIII. mu Arae, a system with four planets</title>
			<authors>Pepe, F.; Correia, A. C. M.; Mayor, M.; Tamuz, O.; Couetdic, J.; Benz, W.; Bertaux, J.-L.; Bouchy, F.; Laskar, J.; Lovis, C.; Naef, D.; Queloz, D.; Santos, N. C.; Sivan, J.-P.; Sosnowska, D.; Udry, S.</authors>
			<journal>Astronomy and Astrophysics, Volume 462, Issue 2, February I 2007, pp.769-776</journal>
			<date>2/2007</date>
			<url>http://cdsads.u-strasbg.fr/abs/2007A%26A...462..769P</url>
		</paper>
		<paper>
			<bibcode>2007A&amp;A...461.1185L</bibcode>
			<title>A diagram to determine the evaporation status of extrasolar planets</title>
			<authors>Lecavelier Des Etangs, A.</authors>
			<journal>Astronomy and Astrophysics, Volume 461, Issue 3, January III 2007, pp.1185-1193</journal>
			<date>1/2007</date>
			<url>http://cdsads.u-strasbg.fr/abs/2007A%26A...461.1185L</url>
		</paper>
		<paper>
			<bibcode>2006ApJ...652L..53B</bibcode>
			<title>Behavior of Apsidal Orientations in Planetary Systems</title>
			<authors>Barnes, Rory; Greenberg, Richard</authors>
			<journal>The Astrophysical Journal, Volume 652, Issue 1, pp. L53-L56.</journal>
			<date>11/2006</date>
			<url>http://cdsads.u-strasbg.fr/abs/2006ApJ...652L..53B</url>
		</paper>
		<paper>
			<bibcode>2006ApJ...651..535E</bibcode>
			<title>On the Possible Properties of Small and Cold Extrasolar Planets: Is OGLE 2005-BLG-390Lb Entirely Frozen?</title>
			<authors>Ehrenreich, David; Lecavelier des Etangs, Alain; Beaulieu, Jean-Philippe; Grasset, Olivier</authors>
			<journal>The Astrophysical Journal, Volume 651, Issue 1, pp. 535-543.</journal>
			<date>11/2006</date>
			<url>http://cdsads.u-strasbg.fr/abs/2006ApJ...651..535E</url>
		</paper>
		<paper>
			<bibcode>2006ApJ...649.1010J</bibcode>
			<title>Habitability of Known Exoplanetary Systems Based on Measured Stellar Properties</title>
			<authors>Jones, Barrie W.; Sleep, P. Nick; Underwood, David R.</authors>
			<journal>The Astrophysical Journal, Volume 649, Issue 2, pp. 1010-1019.</journal>
			<date>10/2006</date>
			<url>http://cdsads.u-strasbg.fr/abs/2006ApJ...649.1010J</url>
		</paper>
		<paper>
			<bibcode>2006ApJ...649..992A</bibcode>
			<title>Effects of Secular Interactions in Extrasolar Planetary Systems</title>
			<authors>Adams, Fred C.; Laughlin, Gregory</authors>
			<journal>The Astrophysical Journal, Volume 649, Issue 2, pp. 992-1003.</journal>
			<date>10/2006</date>
			<url>http://cdsads.u-strasbg.fr/abs/2006ApJ...649..992A</url>
		</paper>
		<paper>
			<bibcode>2006MNRAS.370.1379J</bibcode>
			<title>Data analysis on the extrasolar planets using robust clustering</title>
			<authors>Jiang, Ing-Guey; Yeh, Li-Chin; Hung, Wen-Liang; Yang, Miin-Shen</authors>
			<journal>Monthly Notices of the Royal Astronomical Society, Volume 370, Issue 3, pp. 1379-1392.</journal>
			<date>8/2006</date>
			<url>http://cdsads.u-strasbg.fr/abs/2006MNRAS.370.1379J</url>
		</paper>
		<paper>
			<bibcode>2006MNRAS.369.1267D</bibcode>
			<title>The Hill stability of a binary or planetary system during encounters with a third inclined body</title>
			<authors>Donnison, J. R.</authors>
			<journal>Monthly Notices of the Royal Astronomical Society, Volume 369, Issue 3, pp. 1267-1280.</journal>
			<date>7/2006</date>
			<url>http://cdsads.u-strasbg.fr/abs/2006MNRAS.369.1267D</url>
		</paper>
		<paper>
			<bibcode>2006ApJ...646..505B</bibcode>
			<title>Catalog of Nearby Exoplanets</title>
			<authors>Butler, R. P.; Wright, J. T.; Marcy, G. W.; Fischer, D. A.; Vogt, S. S.; Tinney, C. G.; Jones, H. R. A.; Carter, B. D.; Johnson, J. A.; McCarthy, C.; Penny, A. J.</authors>
			<journal>The Astrophysical Journal, Volume 646, Issue 1, pp. 505-522.</journal>
			<date>7/2006</date>
			<url>http://cdsads.u-strasbg.fr/abs/2006ApJ...646..505B</url>
		</paper>
		<paper>
			<bibcode>2006ApJ...645..688G</bibcode>
			<title>Orbital Configurations and Dynamical Stability of Multiplanet Systems around Sun-like Stars HD 202206, 14 Herculis, HD 37124, and HD 108874</title>
			<authors>Gozdziewski, Krzysztof; Konacki, Maciej; Maciejewski, Andrzej J.</authors>
			<journal>The Astrophysical Journal, Volume 645, Issue 1, pp. 688-703.</journal>
			<date>7/2006</date>
			<url>http://cdsads.u-strasbg.fr/abs/2006ApJ...645..688G</url>
		</paper>
		<paper>
			<bibcode>2005A&amp;A...441..791F</bibcode>
			<title>Oligarchic and giant impact growth of terrestrial planets in the presence of gas giant planet migration</title>
			<authors>Fogg, M. J.; Nelson, R. P.</authors>
			<journal>Astronomy and Astrophysics, Volume 441, Issue 2, October II 2005, pp.791-806</journal>
			<date>10/2005</date>
			<url>http://cdsads.u-strasbg.fr/abs/2005A%26A...441..791F</url>
		</paper>
		<paper>
			<bibcode>2005A&amp;A...440..609B</bibcode>
			<title>Asteroseismology of the planet-hosting star mu Arae. I. The acoustic spectrum</title>
			<authors>Bouchy, F.; Bazot, M.; Santos, N. C.; Vauclair, S.; Sosnowska, D.</authors>
			<journal>Astronomy and Astrophysics, Volume 440, Issue 2, September III 2005, pp.609-614</journal>
			<date>9/2005</date>
			<url>http://cdsads.u-strasbg.fr/abs/2005A%26A...440..609B</url>
		</paper>
		<paper>
			<bibcode>2005ApJ...623.1171T</bibcode>
			<title>Three Low-Mass Planets from the Anglo-Australian Planet Search</title>
			<authors>Tinney, C. G.; Butler, R. Paul; Marcy, Geoffrey W.; Jones, Hugh R. A.; Penny, Alan J.; McCarthy, Chris; Carter, Brad D.; Fischer, Debra A.</authors>
			<journal>The Astrophysical Journal, Volume 623, Issue 2, pp. 1171-1179.</journal>
			<date>4/2005</date>
			<url>http://cdsads.u-strasbg.fr/abs/2005ApJ...623.1171T</url>
		</paper>
		<paper>
			<bibcode>2005ApJ...622.1136G</bibcode>
			<title>Orbital Solutions to the HD 160691 (mu Arae) Doppler Signal</title>
			<authors>Gozdziewski, Krzysztof; Konacki, Maciej; Maciejewski, Andrzej J.</authors>
			<journal>The Astrophysical Journal, Volume 622, Issue 2, pp. 1136-1148.</journal>
			<date>4/2005</date>
			<url>http://cdsads.u-strasbg.fr/abs/2005ApJ...622.1136G</url>
		</paper>
		<paper>
			<bibcode>2005PSci..334...54L</bibcode>
			<title>Quand les planetes perdent leur atmosphere.</title>
			<authors>Lecavelier Des Etangs, A.</authors>
			<journal>Pour la Science, 334, 54-60 (2005)</journal>
			<date>0/2005</date>
			<url>http://cdsads.u-strasbg.fr/abs/2005PSci..334...54L</url>
		</paper>
		<paper>
			<bibcode>2004A&amp;A...426L..19S</bibcode>
			<title>The HARPS survey for southern extra-solar planets. II. A 14 Earth-masses exoplanet around mu Arae</title>
			<authors>Santos, N. C.; Bouchy, F.; Mayor, M.; Pepe, F.; Queloz, D.; Udry, S.; Lovis, C.; Bazot, M.; Benz, W.; Bertaux, J.-L.; Lo Curto, G.; Delfosse, X.; Mordasini, C.; Naef, D.; Sivan, J.-P.; Vauclair, S.</authors>
			<journal>Astronomy and Astrophysics, v.426, p.L19-L23 (2004)</journal>
			<date>10/2004</date>
			<url>http://cdsads.u-strasbg.fr/abs/2004A%26A...426L..19S</url>
		</paper>
	</bibliography>
	<bibliographystar />
</planet>
