<planet>
	<id>KOI 0711.03</id>
	<stellarid>KOI 0711</stellarid>
	<properties>
		<radius>0.2578979</radius>
		<mass>0.0268162076267</mass>
		<orbit>
			<period>124.5230664</period>
			<semimajoraxis>0.491</semimajoraxis>
			<eccentricity>-1</eccentricity>
			<inclination>-1</inclination>
		</orbit>
	</properties>
	<star>
		<kic>9597345</kic>
		<temperature>5502</temperature>
		<mass>-1</mass>
		<radius>1.06</radius>
		<metallicity>0</metallicity>
		<rightascension>19 41 39</rightascension>
		<declination>+46 15 59</declination>
		<distance>642.342752216</distance>
		<mag>13.967</mag>
	</star>
	<multiplicity>3</multiplicity>
</planet>
