<planet>
	<id>KOI 2155.01</id>
	<stellarid>KOI 2155</stellarid>
	<properties>
		<radius>0.1376063</radius>
		<mass>0.0073520730539</mass>
		<orbit>
			<period>4.3394600</period>
			<semimajoraxis>0.051</semimajoraxis>
			<eccentricity>-1</eccentricity>
			<inclination>-1</inclination>
		</orbit>
	</properties>
	<star>
		<kic>12116380</kic>
		<temperature>5389</temperature>
		<mass>-1</mass>
		<radius>0.85</radius>
		<metallicity>0</metallicity>
		<rightascension>19 38 04</rightascension>
		<declination>+50 40 13</declination>
		<distance>732.580043527</distance>
		<mag>14.822</mag>
	</star>
	<multiplicity>1</multiplicity>
</planet>
