<planet>
	<id_exoplaneteu>KOI 2274 b</id_exoplaneteu>
	<name>KOI 2274 b</name>
	<id>KOI 2274 b</id>
	<discoverymethod />
	<properties>
		<mass>0.0211155508903</mass>
		<radius>0.2296476</radius>
		<orbit>
			<period>9.9896497</period>
			<semimajoraxis>0.087</semimajoraxis>
			<eccentricity />
			<inclination />
		</orbit>
	</properties>
	<star>
		<spectraltype />
		<mass>0.0211155508903</mass>
		<radius>0.78</radius>
		<metallicity />
		<temperature />
		<rightascension>19 28 40</rightascension>
		<declination>+43 46 46</declination>
		<angulardistance />
		<distance>979.655301154</distance>
		<magV>15.909</magV>
		<magI />
		<magH />
		<magJ />
		<magK />
	</star>
	<multiplicity>1</multiplicity>
	<discoveryyear />
	<lastupdate />
	<description>This is a Kepler Object of Interest. It has been flagged as a possible transit event but might have not been confirmed to be a planet yet.</description>
	<new />
	<image />
	<imagedescription />
	<list>Kepler Objects of Interest</list>
</planet>
