<planet>
	<id_exoplaneteu>KOI 2542 b</id_exoplaneteu>
	<name>KOI 2542 b</name>
	<id>KOI 2542 b</id>
	<discoverymethod />
	<properties>
		<mass>0.00361616205188</mass>
		<radius>0.0975091</radius>
		<orbit>
			<period>0.7273148</period>
			<semimajoraxis>0.013</semimajoraxis>
			<eccentricity />
			<inclination />
		</orbit>
	</properties>
	<star>
		<spectraltype />
		<mass>0.00361616205188</mass>
		<radius>0.51</radius>
		<metallicity />
		<temperature />
		<rightascension>18 53 36</rightascension>
		<declination>+41 30 58</declination>
		<angulardistance />
		<distance>266.288643044</distance>
		<magV>15.527</magV>
		<magI />
		<magH />
		<magJ />
		<magK />
	</star>
	<multiplicity>1</multiplicity>
	<discoveryyear />
	<lastupdate />
	<description>This is a Kepler Object of Interest. It has been flagged as a possible transit event but might have not been confirmed to be a planet yet.</description>
	<new />
	<image />
	<imagedescription />
	<list>Kepler Objects of Interest</list>
</planet>
