<planet>
	<id_exoplaneteu>KOI 2472 b</id_exoplaneteu>
	<name>KOI 2472 b</name>
	<id>KOI 2472 b</id>
	<discoverymethod />
	<properties>
		<mass>0.0116742400434</mass>
		<radius>0.1722357</radius>
		<orbit>
			<period>2.6075500</period>
			<semimajoraxis>0.038</semimajoraxis>
			<eccentricity />
			<inclination />
		</orbit>
	</properties>
	<star>
		<spectraltype />
		<mass>0.0116742400434</mass>
		<radius>0.98</radius>
		<metallicity />
		<temperature />
		<rightascension>19 11 10</rightascension>
		<declination>+45 58 48</declination>
		<angulardistance />
		<distance>1438.95761758</distance>
		<magV>15.618</magV>
		<magI />
		<magH />
		<magJ />
		<magK />
	</star>
	<multiplicity>1</multiplicity>
	<discoveryyear />
	<lastupdate />
	<description>This is a Kepler Object of Interest. It has been flagged as a possible transit event but might have not been confirmed to be a planet yet.</description>
	<new />
	<image />
	<imagedescription />
	<list>Kepler Objects of Interest</list>
</planet>
