<planet>
	<id>KOI-658 c</id>
	<name>KOI-658 c</name>
	<name>KIC6062088</name>
	<properties>
		<orbit>
			<period>11.3298387</period>
			<semimajoraxis>0.098</semimajoraxis>
		</orbit>
	</properties>
	<star>
		<temperature>5676</temperature>
		<radius>0.88</radius>
		<rightascension>19 48 21</rightascension>
		<declination>+41 23 16</declination>
		<distance>573.306989507</distance>
		<magV>13.989</magV>
	</star>
	<multiplicity>3</multiplicity>
	<list>Kepler Objects of Interest</list>
	<description>This is a Kepler Object of Interest. It has been flagged as a possible transit event but might have not been confirmed to be a planet yet.</description>
</planet>
