<planet>
	<id>KOI-124 b</id>
	<name>KOI-124 b</name>
	<name>KIC11086270</name>
	<properties>
		<orbit>
			<period>31.7198687</period>
			<semimajoraxis>0.200</semimajoraxis>
		</orbit>
	</properties>
	<star>
		<temperature>5899</temperature>
		<radius>1.58</radius>
		<rightascension>19 31 42</rightascension>
		<declination>+48 36 10</declination>
		<distance>684.279721742</distance>
		<magV>12.935</magV>
	</star>
	<multiplicity>2</multiplicity>
	<list>Kepler Objects of Interest</list>
	<description>This is a Kepler Object of Interest. It has been flagged as a possible transit event but might have not been confirmed to be a planet yet.</description>
</planet>
